django_custom_500/__init__.py
django_custom_500/admin.py
django_custom_500/apps.py
django_custom_500/base.py
django_custom_500/forms.py
django_custom_500/handlers.py
django_custom_500/models.py
django_custom_500/views.py
django_custom_500-0.1.1.dist-info/DESCRIPTION.rst
django_custom_500-0.1.1.dist-info/METADATA
django_custom_500-0.1.1.dist-info/RECORD
django_custom_500-0.1.1.dist-info/WHEEL
django_custom_500-0.1.1.dist-info/metadata.json
django_custom_500-0.1.1.dist-info/top_level.txt
